[
	{
		"__TYPE__": "SharedSliceContent",
		"variation": "default",
		"primary": {
			"heading": {
				"__TYPE__": "FieldContent",
				"value": "problem",
				"type": "Text"
			},
			"content_type": {
				"__TYPE__": "FieldContent",
				"value": "Court Interpreter Services",
				"type": "Select"
			},
			"description": {
				"__TYPE__": "StructuredTextContent",
				"value": [
					{
						"type": "paragraph",
						"content": {
							"text": "Ut consectetur amet labore amet ea excepteur ullamco pariatur proident nostrud enim tempor."
						}
					}
				]
			},
			"view_more_text": {
				"__TYPE__": "FieldContent",
				"value": "atmosphere",
				"type": "Text"
			},
			"fallback_item_image": {
				"origin": {
					"id": "main",
					"url": "https://images.unsplash.com/photo-1496181133206-80ce9b88a853",
					"width": 5243,
					"height": 3495
				},
				"url": "https://images.unsplash.com/photo-1496181133206-80ce9b88a853",
				"width": 5243,
				"height": 3495,
				"edit": {
					"zoom": 1,
					"crop": {
						"x": 0,
						"y": 0
					},
					"background": "transparent"
				},
				"credits": null,
				"alt": null,
				"__TYPE__": "ImageContent",
				"thumbnails": {}
			}
		},
		"items": []
	}
]